sumoworkdaycollector/__init__.py
sumoworkdaycollector/api.py
sumoworkdaycollector/main.py
sumoworkdaycollector/sumoworkdaycollector.yaml
sumologic_workday-1.0.3.dist-info/LICENSE
sumologic_workday-1.0.3.dist-info/METADATA
sumologic_workday-1.0.3.dist-info/WHEEL
sumologic_workday-1.0.3.dist-info/entry_points.txt
sumologic_workday-1.0.3.dist-info/top_level.txt
sumologic_workday-1.0.3.dist-info/zip-safe
sumologic_workday-1.0.3.dist-info/RECORD
