Metadata-Version: 2.1
Name: sumologic-workday
Version: 1.0.3
Summary: Sumo Logic collection solution for WorkDay
Home-page: https://github.com/SumoLogic/sumologic-workday
Author: SumoLogic
Author-email: it@sumologic.com, apps-team@sumologic.com
License: PSF
Keywords: sumologic python rest api log management analytics WorkDay agent collector forwarder
Platform: UNKNOWN
Classifier: Development Status :: 4 - Beta
Classifier: Intended Audience :: Developers
Classifier: Programming Language :: Python :: 2.7
Classifier: Programming Language :: Python :: 3.7
Classifier: Operating System :: OS Independent
Requires-Dist: sumologic-appclient-sdk (>=1.0.17)
Provides-Extra: all
Requires-Dist: boto3 (>=1.9.66) ; extra == 'all'
Requires-Dist: botocore (>=1.12.66) ; extra == 'all'
Requires-Dist: google-api-python-client (>=1.7.8) ; extra == 'all'
Requires-Dist: oauth2client (>=4.1.3) ; extra == 'all'
Requires-Dist: google-cloud-datastore (>=1.7.3) ; extra == 'all'
Requires-Dist: azure-cosmosdb-table (>=1.0.5) ; extra == 'all'
Requires-Dist: bson (>=0.5.8) ; extra == 'all'
Provides-Extra: aws
Requires-Dist: boto3 (>=1.9.66) ; extra == 'aws'
Requires-Dist: botocore (>=1.12.66) ; extra == 'aws'
Provides-Extra: azure
Requires-Dist: azure-cosmosdb-table (>=1.0.5) ; extra == 'azure'
Requires-Dist: bson (>=0.5.8) ; extra == 'azure'
Provides-Extra: dev
Requires-Dist: twine ; extra == 'dev'
Requires-Dist: wheel ; extra == 'dev'
Requires-Dist: setuptools ; extra == 'dev'
Requires-Dist: check-manifest ; extra == 'dev'
Requires-Dist: aws-sam-cli ; extra == 'dev'
Requires-Dist: awscli ; extra == 'dev'
Provides-Extra: gcp
Requires-Dist: google-api-python-client (>=1.7.8) ; extra == 'gcp'
Requires-Dist: oauth2client (>=4.1.3) ; extra == 'gcp'
Requires-Dist: google-cloud-datastore (>=1.7.3) ; extra == 'gcp'
